Metadata-Version: 2.4
Name: autodg
Version: 1.0.3
Summary: A modular Python API analyzer for Flask, FastAPI, Django, and DRF with AI-powered documentation generation
Author-email: Dhinagaran <atsupp02@gmail.com>
License: MIT
Project-URL: Homepage, https://github.com/Airavath-Technologies/autodg
Project-URL: Repository, https://github.com/Airavath-Technologies/autodg
Project-URL: Documentation, https://github.com/Airavath-Technologies/autodg#readme
Keywords: api,documentation,analyzer,flask,fastapi,django,drf,ai,llm
Classifier: Development Status :: 4 - Beta
Classifier: Intended Audience :: Developers
Classifier: License :: OSI Approved :: MIT License
Classifier: Programming Language :: Python :: 3
Classifier: Programming Language :: Python :: 3.11
Classifier: Programming Language :: Python :: 3.12
Classifier: Topic :: Software Development :: Documentation
Classifier: Topic :: Software Development :: Code Generators
Requires-Python: >=3.11
License-File: LICENSE
Requires-Dist: requests>=2.31.0
Requires-Dist: pyyaml>=6.0
Requires-Dist: tqdm>=4.0.0
Requires-Dist: loguru>=0.7.0
Provides-Extra: openai
Requires-Dist: openai>=1.0.0; extra == "openai"
Provides-Extra: claude
Requires-Dist: anthropic>=0.18.0; extra == "claude"
Provides-Extra: gemini
Requires-Dist: google-generativeai>=0.3.0; extra == "gemini"
Provides-Extra: all
Requires-Dist: openai>=1.0.0; extra == "all"
Requires-Dist: anthropic>=0.18.0; extra == "all"
Requires-Dist: google-generativeai>=0.3.0; extra == "all"
Dynamic: license-file
